Metadata-Version: 1.0
Name: gobi-probability
Version: 1.0
Summary: Gaussian distributions and binomial distributions
Home-page: UNKNOWN
Author: Sambili Tonny
Author-email: synnotlee@gmail.com
License: UNKNOWN
Platform: UNKNOWN
